kyuda/__init__.py
kyuda/script_helpers.py
kyuda-0.3.0.dist-info/LICENSE
kyuda-0.3.0.dist-info/LICENSE-MIT
kyuda-0.3.0.dist-info/METADATA
kyuda-0.3.0.dist-info/WHEEL
kyuda-0.3.0.dist-info/top_level.txt
kyuda-0.3.0.dist-info/RECORD
