Metadata-Version: 2.1
Name: kyuda
Version: 0.3.0
Summary: UNKNOWN
Home-page: https://github.com/KyudaHQ/kyuda-py
Author: Kyuda
Author-email: hello@kyuda.io
Maintainer: Kyuda
Maintainer-email: hello@kyuda.io
License: MIT
Platform: UNKNOWN
Classifier: Development Status :: 4 - Beta
Classifier: Intended Audience :: Developers
Classifier: License :: OSI Approved :: MIT License
Classifier: Natural Language :: English
Classifier: Operating System :: OS Independent
Classifier: Programming Language :: Python :: 2.7
Classifier: Programming Language :: Python :: 3.5
Classifier: Programming Language :: Python :: 3.6
Classifier: Programming Language :: Python :: Implementation :: CPython
Classifier: Programming Language :: Python :: Implementation :: PyPy
License-File: LICENSE
License-File: LICENSE-MIT
